checkpointe/__init__.py
checkpointe/functions.py
checkpointe/test.py
checkpointe-0.2.5.dist-info/LICENSE
checkpointe-0.2.5.dist-info/METADATA
checkpointe-0.2.5.dist-info/WHEEL
checkpointe-0.2.5.dist-info/top_level.txt
checkpointe-0.2.5.dist-info/RECORD
