Metadata-Version: 2.1
Name: checkpointe
Version: 0.2.5
Summary: A simple process timer for python scripts.
Home-page: https://github.com/e-kirkland/checkpointe
Author: Eddie Kirkland
Author-email: eddie@kdsolutions.co
License: Apache License 2.0
Platform: UNKNOWN
Requires-Dist: datetime
